tb/__init__.py
tb/py.typed
trenchbroom_api-0.1.5.dist-info/METADATA
trenchbroom_api-0.1.5.dist-info/WHEEL
trenchbroom_api-0.1.5.dist-info/top_level.txt
trenchbroom_api-0.1.5.dist-info/RECORD
