Metadata-Version: 2.4
Name: trenchbroom-api
Version: 0.1.5
Summary: Type stubs for TrenchBroom embedded Python module `tb`.
Author: XiangXtreme
License-Expression: GPL-3.0-or-later
Keywords: trenchbroom,scripting,typing
Classifier: Development Status :: 3 - Alpha
Classifier: Intended Audience :: Developers
Classifier: Programming Language :: Python :: 3
Classifier: Programming Language :: Python :: 3 :: Only
Classifier: Typing :: Typed
Requires-Python: >=3.10
